invenio_openid_connect/__init__.py
invenio_openid_connect/ext.py
invenio_openid_connect/remote.py
invenio_openid_connect/signals.py
invenio_openid_connect/utils.py
invenio_openid_connect/version.py
invenio_openid_connect/views.py
invenio_openid_connect/translations/messages.pot
invenio_openid_connect/translations/cs/LC_MESSAGES/messages.po
invenio_openid_connect/translations/en/LC_MESSAGES/messages.po
invenio_openid_connect-2.1.0.dist-info/AUTHORS.rst
invenio_openid_connect-2.1.0.dist-info/LICENSE
invenio_openid_connect-2.1.0.dist-info/METADATA
invenio_openid_connect-2.1.0.dist-info/WHEEL
invenio_openid_connect-2.1.0.dist-info/entry_points.txt
invenio_openid_connect-2.1.0.dist-info/top_level.txt
invenio_openid_connect-2.1.0.dist-info/RECORD
