Metadata-Version: 2.1
Name: invenio-openid-connect
Version: 2.1.0
Summary: Invenio OpenID Connect Auth Backend
Home-page: https://github.com/oarepo/invenio-openid-connect
Author: Miroslav Bauer
Author-email: bauer@cesnet.cz
License: MIT
Keywords: OpenID Invenio
Platform: any
Classifier: Environment :: Web Environment
Classifier: Intended Audience :: Developers
Classifier: License :: OSI Approved :: MIT License
Classifier: Operating System :: OS Independent
Classifier: Programming Language :: Python
Classifier: Topic :: Internet :: WWW/HTTP :: Dynamic Content
Classifier: Topic :: Software Development :: Libraries :: Python Modules
Classifier: Programming Language :: Python :: 2
Classifier: Programming Language :: Python :: 2.7
Classifier: Programming Language :: Python :: 3
Classifier: Programming Language :: Python :: 3.5
Classifier: Development Status :: 4 - Beta
Requires-Dist: flask-oauthlib
Requires-Dist: invenio-oauthclient
Requires-Dist: munch
Requires-Dist: pyhumps (>=1.6.1)
Provides-Extra: tests
Requires-Dist: oarepo[tests] (~=3.3.0) ; extra == 'tests'
